% Frames

% Attack => Et attack paa det eksempel Dennis gennemgaar  (scenariet)

% Countermeasures => Vis hvordan et countermeasure kunne vaere implementeret paa det eksempel

\begin{frame}[fragile]{Introduction}
\begin{center}
	\begin{itemize}
	\item Smart cards are increasingly being integrated in every day life (credit cards, Rejsekort, etc.)
	\item Estonia uses smart cards as national cards \footnote{https://e-estonia.com/component/electronic-id-card/}
		\begin{itemize}
		\item[-] Travel within EU borders
		\item[-] Health insurance card
		\item[-] e-Prescriptions
		\item[-] Other countries are interested in their solution
		\end{itemize}
	\end{itemize}
\end{center}
\end{frame}

\begin{frame}[fragile]{\large How can bit flips be introduced and why are they a problem?}
Bit flips can present security issues, such as validation bypassing and control of other applets on a smart card\\~\\
Different sources:\\~\\
	\begin{itemize}
	\item Cosmic rays
	\item Radiation (electromagnetic, infrared, atomic)
	\item Physical damage
	\end{itemize}
	
The sources have different levels of precision
\end{frame}
\begin{frame}[fragile]{Field of Bit \& Instruction Differentiation}
\begin{itemize}
\item We assume that FoB is implemented in the JCVM
\item What if FoB was not implemented?
\end{itemize}
\begin{table}
\centering
\begin{tabular}{|c|c|c|c|c|c|}
\hline PC & 4 & 5 & 6   \\ 
\hline ifeq & X & R & R \\ 
\hline goto & X & R & R \\ 
\hline newInst & X & R & X \\ 
\hline 
\end{tabular} 
\end{table}
\end{frame}

\begin{frame}[fragile]{Field of Bit \& Instruction Differentiation}
\begin{minipage}{.45\textwidth}
\begin{lstlisting}[frame=single]
...
 1: invokespecial #6
 4: ifeq 15
 7: new           #3
10: dup
11: invokespecial #7
14: athrow
15: aload_0
16: invokespecial #8
...
\end{lstlisting}
\end{minipage}%
\hspace{20px}
\begin{minipage}{0.45\textwidth}
\begin{lstlisting}[frame=single]
...
 1: invokespecial #6
 4: goto 15
 7: new           #3
10: dup
11: invokespecial #7
14: athrow
15: aload_0
16: invokespecial #8
...
\end{lstlisting}
\end{minipage}
\begin{center}
$ifeq = 0x60,\:goto = 0x70$
\end{center}
\end{frame}

\begin{frame}[fragile]{Field of Bit \& Instruction Differentiation}
\begin{itemize}
\item What if FoB was not implemented in the JCVM?
\item Mapping of instructions to opcodes could be changed to improve security
\end{itemize}
\begin{table}
\centering
\begin{tabular}{|c|c|c|c|c|c|}
\hline PC & 4 & 5 & 6   \\ 
\hline ifeq & X & R & R \\ 
\hline goto & X & R & R \\ 
\hline inst & X & R & X \\ 
\hline 
\end{tabular} 
\end{table}
\end{frame}

\begin{frame}[fragile]{Our Solution}
\begin{center}
\begin{figure}
\def\svgwidth{\columnwidth}
\input{figures/workflow_new_blank.tex}
\caption{The workflow of the solution, from Java bytecode to UPPAAL SMC model and assessment of the modelled program.}
\label{fig:workflow_new}
\end{figure}
\end{center}
\end{frame}

%\begin{frame}[fragile]{Modelling Multiple Bit Flips in UPPAAL}
%\begin{itemize}
%\item Limitations of current fault model
%\subitem Semantics for describing failed reads / writes
%\item Multiple bit flips	
%\end{itemize}
%\end{frame}

\begin{frame}[fragile]{Extended Solution}


\begin{figure}
\centering
\includegraphics[scale=0.65]{figures/workflow.pdf}
\caption{\footnotesize The extended solution, consisting of automatic rewriting, UPPAAL SMC model conversion, fault injection and countermeasure recommendation.}
\label{test}
\end{figure}
\end{frame}